{"timeline": {"headline": "\u30c6\u30aa\u30d5\u30a3\u30eb\u30fb\u30a2\u30ec\u30af\u30b5\u30f3\u30c9\u30eb\u30fb\u30b9\u30bf\u30f3\u30e9\u30f3", "text": "<p>Artist timeline</p>", "type": "default", "date": [{"headline": "\u56fd\u7acb\u97f3\u697d\u30a2\u30ab\u30c7\u30df\u30fc\u3001\u30d0\u30ec\u30a8\u516c\u6f14\u300c\u5922\u300d", "startDate": "1889", "endDate": "1889", "text": "<p>On display at: <a href='http://lod.ac/id/8221'>\u5fb3\u5cf6\u770c\u7acb\u8fd1\u4ee3\u7f8e\u8853\u9928</a></p>"}, {"headline": "\u9ad8\u540d\u306a\u300c\u9ed2\u732b\u300d\u4e00\u5ea7\u8fd1\u65e5\u6765\u6f14", "startDate": "1896", "endDate": "1896", "text": "<p>On display at: <a href='http://lod.ac/id/8221'>\u5fb3\u5cf6\u770c\u7acb\u8fd1\u4ee3\u7f8e\u8853\u9928</a></p>"}, {"headline": "\u6f14\u5287\u300c\u5c45\u9152\u5c4b\u300d\u30dd\u30eb\u30c8=\u30b5\u30f3=\u30de\u30eb\u30bf\u30f3\u5287\u5834", "startDate": "1900", "endDate": "1900", "text": "<p>On display at: <a href='http://lod.ac/id/8221'>\u5fb3\u5cf6\u770c\u7acb\u8fd1\u4ee3\u7f8e\u8853\u9928</a></p>"}, {"headline": "\u300c\u30b9\u30bf\u30f3\u30e9\u30f3\u306b\u3088\u308b\u30c7\u30c3\u30b5\u30f3\u3068\u6cb9\u5f69\u5c55\u300d\u30dd\u30b9\u30bf\u30fc", "startDate": "1894", "endDate": "1894", "text": "<p>On display at: <a href='http://lod.ac/id/8221'>\u5fb3\u5cf6\u770c\u7acb\u8fd1\u4ee3\u7f8e\u8853\u9928</a></p>"}, {"headline": "\u4ed5\u4e8b\u5e30\u308a\u306e\u304a\u91dd\u5b50\u305f\u3061", "startDate": "1900", "endDate": "1900", "text": "<p>On display at: <a href='http://lod.ac/id/3172'>\u6a2a\u6d5c\u7f8e\u8853\u9928</a></p>"}, {"headline": "\u5973\u6027\u7fd2\u4f5c", "startDate": "1902", "endDate": "1902", "text": "<p>On display at: <a href='http://lod.ac/id/3172'>\u6a2a\u6d5c\u7f8e\u8853\u9928</a></p>"}, {"headline": "\u300c\u30e9\u30ab\u30a6\u300d\u306e\u30dd\u30b9\u30bf\u30fc", "startDate": "1905", "endDate": "1905", "text": "<p>On display at: <a href='http://lod.ac/id/3172'>\u6a2a\u6d5c\u7f8e\u8853\u9928</a></p>"}, {"headline": "\u590f:\u624b\u647a\u308a\u306e\u4e0a\u306e\u732b", "startDate": "1909", "endDate": "1909", "text": "<p>On display at: <a href='http://lod.ac/id/8221'>\u5fb3\u5cf6\u770c\u7acb\u8fd1\u4ee3\u7f8e\u8853\u9928</a></p>"}, {"headline": "\u30bb\u30eb\u30d3\u30a2\u5175", "startDate": "1916", "endDate": "1916", "text": "<p>On display at: <a href='http://lod.ac/id/3172'>\u6a2a\u6d5c\u7f8e\u8853\u9928</a></p>"}]}}